{"latency_ms":9,"trial_data":{"TrialEventData":[{"nodeId":71,"eventType":"move","reward":0,"time":1.769},{"nodeId":82,"eventType":"move","reward":0,"time":1.902},{"nodeId":93,"eventType":"move","reward":0,"time":2.083},{"nodeId":94,"eventType":"move","reward":0,"time":2.244},{"nodeId":95,"eventType":"move","reward":0,"time":2.561},{"nodeId":96,"eventType":"move","reward":0,"time":2.651},{"nodeId":97,"eventType":"move","reward":0,"time":2.762},{"nodeId":97,"eventType":"collect","reward":0,"time":3.073},{"nodeId":96,"eventType":"move","reward":0,"time":3.241},{"nodeId":96,"eventType":"collect","reward":0,"time":3.386},{"nodeId":95,"eventType":"move","reward":0,"time":3.515},{"nodeId":106,"eventType":"move","reward":0,"time":3.671},{"nodeId":117,"eventType":"move","reward":0,"time":3.799},{"nodeId":117,"eventType":"collect","reward":0,"time":4.064},{"nodeId":118,"eventType":"move","reward":0,"time":4.271},{"nodeId":119,"eventType":"move","reward":0,"time":4.469},{"nodeId":119,"eventType":"collect","reward":0,"time":4.99},{"nodeId":120,"eventType":"move","reward":0,"time":5.118},{"nodeId":109,"eventType":"move","reward":0,"time":5.298},{"nodeId":98,"eventType":"move","reward":0,"time":5.431},{"nodeId":87,"eventType":"move","reward":0,"time":5.512},{"nodeId":98,"eventType":"move","reward":0,"time":5.98},{"nodeId":98,"eventType":"collect","reward":0,"time":6.178},{"nodeId":87,"eventType":"move","reward":0,"time":6.311},{"nodeId":76,"eventType":"move","reward":0,"time":6.431},{"nodeId":65,"eventType":"move","reward":0,"time":6.499},{"nodeId":54,"eventType":"move","reward":0,"time":6.601},{"nodeId":43,"eventType":"move","reward":0,"time":6.698},{"nodeId":32,"eventType":"move","reward":0,"time":6.785},{"nodeId":21,"eventType":"move","reward":0,"time":6.889},{"nodeId":21,"eventType":"collect","reward":0,"time":7.262},{"nodeId":20,"eventType":"move","reward":0,"time":7.416},{"nodeId":19,"eventType":"move","reward":0,"time":7.593},{"nodeId":18,"eventType":"move","reward":0,"time":7.695},{"nodeId":17,"eventType":"move","reward":0,"time":7.781},{"nodeId":16,"eventType":"move","reward":0,"time":7.886},{"nodeId":15,"eventType":"move","reward":0,"time":7.976},{"nodeId":14,"eventType":"move","reward":0,"time":8.37},{"nodeId":14,"eventType":"collect","reward":0,"time":8.805},{"nodeId":15,"eventType":"move","reward":0,"time":9.678},{"nodeId":14,"eventType":"move","reward":0,"time":9.901},{"nodeId":13,"eventType":"move","reward":0,"time":9.992},{"nodeId":13,"eventType":"collect","reward":0,"time":10.245},{"nodeId":14,"eventType":"move","reward":0,"time":10.382},{"nodeId":15,"eventType":"move","reward":0,"time":10.502},{"nodeId":16,"eventType":"move","reward":0,"time":10.591},{"nodeId":27,"eventType":"move","reward":0,"time":10.86},{"nodeId":38,"eventType":"move","reward":0,"time":11.062},{"nodeId":49,"eventType":"move","reward":0,"time":11.15},{"nodeId":60,"eventType":"move","reward":0,"time":11.684},{"nodeId":60,"eventType":"finish","reward":0,"time":11.912}]}}