{"latency_ms":10,"trial_data":{"TrialEventData":[{"nodeId":49,"eventType":"move","reward":0,"time":1.361},{"nodeId":38,"eventType":"move","reward":0,"time":1.606},{"nodeId":27,"eventType":"move","reward":0,"time":1.81},{"nodeId":26,"eventType":"move","reward":0,"time":2.065},{"nodeId":26,"eventType":"collect","reward":0,"time":2.241},{"nodeId":25,"eventType":"move","reward":0,"time":2.422},{"nodeId":24,"eventType":"move","reward":0,"time":2.621},{"nodeId":24,"eventType":"collect","reward":0,"time":2.74},{"nodeId":35,"eventType":"move","reward":0,"time":3.155},{"nodeId":46,"eventType":"move","reward":0,"time":3.356},{"nodeId":45,"eventType":"move","reward":0,"time":3.637},{"nodeId":44,"eventType":"move","reward":0,"time":3.804},{"nodeId":33,"eventType":"move","reward":0,"time":4.224},{"nodeId":33,"eventType":"collect","reward":0,"time":4.372},{"nodeId":22,"eventType":"move","reward":0,"time":4.577},{"nodeId":22,"eventType":"collect","reward":0,"time":4.71},{"nodeId":11,"eventType":"move","reward":0,"time":4.888},{"nodeId":0,"eventType":"move","reward":0,"time":5.846},{"nodeId":1,"eventType":"move","reward":0,"time":6.002},{"nodeId":2,"eventType":"move","reward":0,"time":6.122},{"nodeId":3,"eventType":"move","reward":0,"time":6.196},{"nodeId":4,"eventType":"move","reward":0,"time":6.322},{"nodeId":3,"eventType":"move","reward":0,"time":6.621},{"nodeId":3,"eventType":"collect","reward":0,"time":6.777},{"nodeId":4,"eventType":"move","reward":0,"time":6.879},{"nodeId":5,"eventType":"move","reward":0,"time":6.974},{"nodeId":6,"eventType":"move","reward":0,"time":7.201},{"nodeId":7,"eventType":"move","reward":0,"time":7.489},{"nodeId":18,"eventType":"move","reward":0,"time":7.734},{"nodeId":29,"eventType":"move","reward":0,"time":7.906},{"nodeId":29,"eventType":"collect","reward":0,"time":8.249},{"nodeId":40,"eventType":"move","reward":0,"time":8.466},{"nodeId":41,"eventType":"move","reward":0,"time":8.683},{"nodeId":41,"eventType":"collect","reward":0,"time":8.932},{"nodeId":40,"eventType":"move","reward":0,"time":9.137},{"nodeId":39,"eventType":"move","reward":0,"time":9.327},{"nodeId":38,"eventType":"move","reward":0,"time":9.469},{"nodeId":49,"eventType":"move","reward":0,"time":9.759},{"nodeId":60,"eventType":"move","reward":0,"time":9.942},{"nodeId":60,"eventType":"finish","reward":0,"time":10.827}]}}