{"latency_ms":1094,"trial_data":{"TrialEventData":[{"nodeId":71,"eventType":"move","reward":0,"time":1.628},{"nodeId":82,"eventType":"move","reward":0,"time":1.802},{"nodeId":81,"eventType":"move","reward":0,"time":2.003},{"nodeId":80,"eventType":"move","reward":0,"time":2.325},{"nodeId":79,"eventType":"move","reward":0,"time":2.518},{"nodeId":90,"eventType":"move","reward":0,"time":2.857},{"nodeId":101,"eventType":"move","reward":0,"time":3.054},{"nodeId":112,"eventType":"move","reward":0,"time":3.237},{"nodeId":112,"eventType":"collect","reward":0,"time":3.444},{"nodeId":113,"eventType":"move","reward":0,"time":3.753},{"nodeId":114,"eventType":"move","reward":0,"time":4.122},{"nodeId":115,"eventType":"move","reward":0,"time":4.305},{"nodeId":104,"eventType":"move","reward":0,"time":4.534},{"nodeId":115,"eventType":"move","reward":0,"time":4.94},{"nodeId":114,"eventType":"move","reward":0,"time":5.173},{"nodeId":113,"eventType":"move","reward":0,"time":5.381},{"nodeId":112,"eventType":"move","reward":0,"time":5.528},{"nodeId":111,"eventType":"move","reward":0,"time":5.674},{"nodeId":111,"eventType":"collect","reward":0,"time":5.986},{"nodeId":null,"eventType":"overfilled","reward":0,"time":5.986},{"nodeId":112,"eventType":"move","reward":0,"time":6.174},{"nodeId":113,"eventType":"move","reward":0,"time":6.369},{"nodeId":114,"eventType":"move","reward":0,"time":6.542},{"nodeId":115,"eventType":"move","reward":0,"time":6.872},{"nodeId":104,"eventType":"move","reward":0,"time":7.362},{"nodeId":93,"eventType":"move","reward":0,"time":7.803},{"nodeId":104,"eventType":"move","reward":0,"time":8.402},{"nodeId":105,"eventType":"move","reward":0,"time":8.635},{"nodeId":106,"eventType":"move","reward":0,"time":9.103},{"nodeId":105,"eventType":"move","reward":0,"time":9.754},{"nodeId":105,"eventType":"collect","reward":0,"time":9.988},{"nodeId":null,"eventType":"overfilled","reward":0,"time":9.988},{"nodeId":106,"eventType":"move","reward":0,"time":10.171},{"nodeId":107,"eventType":"move","reward":0,"time":10.39},{"nodeId":108,"eventType":"move","reward":0,"time":10.621},{"nodeId":108,"eventType":"collect","reward":0,"time":10.836},{"nodeId":null,"eventType":"overfilled","reward":0,"time":10.836},{"nodeId":97,"eventType":"move","reward":0,"time":11.058},{"nodeId":86,"eventType":"move","reward":0,"time":11.285},{"nodeId":75,"eventType":"move","reward":0,"time":11.459},{"nodeId":64,"eventType":"move","reward":0,"time":11.668},{"nodeId":63,"eventType":"move","reward":0,"time":12.353},{"nodeId":62,"eventType":"move","reward":0,"time":12.72},{"nodeId":51,"eventType":"move","reward":0,"time":13.046},{"nodeId":62,"eventType":"move","reward":0,"time":13.687},{"nodeId":73,"eventType":"move","reward":0,"time":14.338},{"nodeId":73,"eventType":"collect","reward":0,"time":14.775},{"nodeId":null,"eventType":"overfilled","reward":0,"time":14.775},{"nodeId":62,"eventType":"move","reward":0,"time":15.173},{"nodeId":61,"eventType":"move","reward":0,"time":15.441},{"nodeId":60,"eventType":"move","reward":0,"time":15.627},{"nodeId":61,"eventType":"move","reward":0,"time":16.606},{"nodeId":50,"eventType":"move","reward":0,"time":17.092},{"nodeId":51,"eventType":"move","reward":0,"time":17.455},{"nodeId":51,"eventType":"collect","reward":0,"time":17.803},{"nodeId":null,"eventType":"overfilled","reward":0,"time":17.803},{"nodeId":62,"eventType":"move","reward":0,"time":18.654},{"nodeId":73,"eventType":"move","reward":0,"time":20.028},{"nodeId":72,"eventType":"move","reward":0,"time":20.27},{"nodeId":61,"eventType":"move","reward":0,"time":20.955},{"nodeId":60,"eventType":"move","reward":0,"time":21.207}]}}