{"latency_ms":29,"trial_data":{"TrialEventData":[{"nodeId":61,"eventType":"move","reward":0,"time":1.64},{"nodeId":72,"eventType":"move","reward":0,"time":1.806},{"nodeId":83,"eventType":"move","reward":0,"time":2.011},{"nodeId":94,"eventType":"move","reward":0,"time":2.203},{"nodeId":95,"eventType":"move","reward":0,"time":2.527},{"nodeId":95,"eventType":"collect","reward":0,"time":3.003},{"nodeId":106,"eventType":"move","reward":0,"time":3.302},{"nodeId":107,"eventType":"move","reward":0,"time":3.489},{"nodeId":107,"eventType":"collect","reward":0,"time":3.827},{"nodeId":118,"eventType":"move","reward":0,"time":4.143},{"nodeId":118,"eventType":"collect","reward":0,"time":4.369},{"nodeId":117,"eventType":"move","reward":0,"time":4.558},{"nodeId":117,"eventType":"collect","reward":0,"time":4.785},{"nodeId":106,"eventType":"move","reward":0,"time":5.037},{"nodeId":105,"eventType":"move","reward":0,"time":5.189},{"nodeId":105,"eventType":"collect","reward":0,"time":6.341},{"nodeId":94,"eventType":"move","reward":0,"time":6.838},{"nodeId":83,"eventType":"move","reward":0,"time":7.078},{"nodeId":72,"eventType":"move","reward":0,"time":7.356},{"nodeId":61,"eventType":"move","reward":0,"time":7.59},{"nodeId":50,"eventType":"move","reward":0,"time":7.807},{"nodeId":61,"eventType":"move","reward":0,"time":9.508},{"nodeId":60,"eventType":"move","reward":0,"time":9.822},{"nodeId":60,"eventType":"finish","reward":0,"time":11.901}]}}