{"latency_ms":140,"trial_data":{"TrialEventData":[{"nodeId":71,"eventType":"move","reward":0,"time":1.362},{"nodeId":82,"eventType":"move","reward":0,"time":1.639},{"nodeId":93,"eventType":"move","reward":0,"time":1.853},{"nodeId":82,"eventType":"move","reward":0,"time":2.478},{"nodeId":81,"eventType":"move","reward":0,"time":2.669},{"nodeId":80,"eventType":"move","reward":0,"time":3.069},{"nodeId":80,"eventType":"collect","reward":0,"time":3.353},{"nodeId":81,"eventType":"move","reward":0,"time":3.573},{"nodeId":92,"eventType":"move","reward":0,"time":3.796},{"nodeId":91,"eventType":"move","reward":0,"time":4.068},{"nodeId":91,"eventType":"collect","reward":0,"time":4.273},{"nodeId":102,"eventType":"move","reward":0,"time":4.469},{"nodeId":103,"eventType":"move","reward":0,"time":4.668},{"nodeId":103,"eventType":"collect","reward":0,"time":4.808},{"nodeId":102,"eventType":"move","reward":0,"time":5.168},{"nodeId":102,"eventType":"collect","reward":0,"time":5.336},{"nodeId":101,"eventType":"move","reward":0,"time":5.696},{"nodeId":100,"eventType":"move","reward":0,"time":5.905},{"nodeId":100,"eventType":"collect","reward":0,"time":6.15},{"nodeId":99,"eventType":"move","reward":0,"time":6.438},{"nodeId":88,"eventType":"move","reward":0,"time":6.727},{"nodeId":89,"eventType":"move","reward":0,"time":6.889},{"nodeId":89,"eventType":"collect","reward":0,"time":7.102},{"nodeId":null,"eventType":"overfilled","reward":0,"time":7.102},{"nodeId":90,"eventType":"move","reward":0,"time":7.786},{"nodeId":91,"eventType":"move","reward":0,"time":7.968},{"nodeId":92,"eventType":"move","reward":0,"time":8.153},{"nodeId":103,"eventType":"move","reward":0,"time":8.74},{"nodeId":104,"eventType":"move","reward":0,"time":8.937},{"nodeId":105,"eventType":"move","reward":0,"time":9.157},{"nodeId":106,"eventType":"move","reward":0,"time":9.345},{"nodeId":106,"eventType":"collect","reward":0,"time":9.654},{"nodeId":95,"eventType":"move","reward":0,"time":9.888},{"nodeId":84,"eventType":"move","reward":0,"time":10.087},{"nodeId":73,"eventType":"move","reward":0,"time":10.274},{"nodeId":62,"eventType":"move","reward":0,"time":10.439},{"nodeId":61,"eventType":"move","reward":0,"time":10.657},{"nodeId":60,"eventType":"move","reward":0,"time":10.854}]}}