{"latency_ms":204,"trial_data":{"TrialEventData":[{"nodeId":59,"eventType":"move","reward":0,"time":1.468},{"nodeId":58,"eventType":"move","reward":0,"time":1.632},{"nodeId":69,"eventType":"move","reward":0,"time":1.819},{"nodeId":69,"eventType":"collect","reward":0,"time":2.152},{"nodeId":68,"eventType":"move","reward":0,"time":2.332},{"nodeId":68,"eventType":"collect","reward":0,"time":2.619},{"nodeId":67,"eventType":"move","reward":0,"time":2.848},{"nodeId":66,"eventType":"move","reward":0,"time":3.198},{"nodeId":66,"eventType":"collect","reward":0,"time":3.481},{"nodeId":77,"eventType":"move","reward":0,"time":3.682},{"nodeId":88,"eventType":"move","reward":0,"time":3.833},{"nodeId":88,"eventType":"collect","reward":0,"time":4.081},{"nodeId":99,"eventType":"move","reward":0,"time":4.289},{"nodeId":99,"eventType":"collect","reward":0,"time":4.433},{"nodeId":100,"eventType":"move","reward":0,"time":4.63},{"nodeId":101,"eventType":"move","reward":0,"time":4.798},{"nodeId":102,"eventType":"move","reward":0,"time":4.965},{"nodeId":103,"eventType":"move","reward":0,"time":5.147},{"nodeId":103,"eventType":"collect","reward":0,"time":5.414},{"nodeId":92,"eventType":"move","reward":0,"time":5.598},{"nodeId":81,"eventType":"move","reward":0,"time":5.766},{"nodeId":70,"eventType":"move","reward":0,"time":6.096},{"nodeId":59,"eventType":"move","reward":0,"time":6.283},{"nodeId":58,"eventType":"move","reward":0,"time":7.246},{"nodeId":47,"eventType":"move","reward":0,"time":7.397},{"nodeId":36,"eventType":"move","reward":0,"time":7.618},{"nodeId":25,"eventType":"move","reward":0,"time":7.799},{"nodeId":25,"eventType":"collect","reward":0,"time":8.115},{"nodeId":14,"eventType":"move","reward":0,"time":8.348},{"nodeId":15,"eventType":"move","reward":0,"time":8.533},{"nodeId":15,"eventType":"collect","reward":0,"time":8.771},{"nodeId":16,"eventType":"move","reward":0,"time":8.983},{"nodeId":17,"eventType":"move","reward":0,"time":9.151},{"nodeId":18,"eventType":"move","reward":0,"time":9.316},{"nodeId":18,"eventType":"collect","reward":0,"time":9.831},{"nodeId":17,"eventType":"move","reward":0,"time":9.997},{"nodeId":17,"eventType":"collect","reward":0,"time":10.265},{"nodeId":28,"eventType":"move","reward":0,"time":10.481},{"nodeId":39,"eventType":"move","reward":0,"time":10.665},{"nodeId":40,"eventType":"move","reward":0,"time":10.916},{"nodeId":40,"eventType":"collect","reward":0,"time":11.437},{"nodeId":39,"eventType":"move","reward":0,"time":11.9},{"nodeId":38,"eventType":"move","reward":0,"time":12.13},{"nodeId":37,"eventType":"move","reward":0,"time":12.631},{"nodeId":48,"eventType":"move","reward":0,"time":12.847},{"nodeId":49,"eventType":"move","reward":0,"time":13.047},{"nodeId":60,"eventType":"move","reward":0,"time":13.246}]}}