{"latency_ms":23,"trial_data":{"TrialEventData":[{"nodeId":71,"eventType":"move","reward":0,"time":2.061},{"nodeId":70,"eventType":"move","reward":0,"time":2.703},{"nodeId":71,"eventType":"move","reward":0,"time":3.208},{"nodeId":60,"eventType":"move","reward":0,"time":3.458},{"nodeId":49,"eventType":"move","reward":0,"time":3.668},{"nodeId":48,"eventType":"move","reward":0,"time":3.991},{"nodeId":37,"eventType":"move","reward":0,"time":4.303},{"nodeId":37,"eventType":"collect","reward":0,"time":5.739},{"nodeId":36,"eventType":"move","reward":0,"time":5.919},{"nodeId":25,"eventType":"move","reward":0,"time":6.202},{"nodeId":14,"eventType":"move","reward":0,"time":6.406},{"nodeId":14,"eventType":"collect","reward":0,"time":6.585},{"nodeId":13,"eventType":"move","reward":0,"time":6.741},{"nodeId":24,"eventType":"move","reward":0,"time":7.048},{"nodeId":35,"eventType":"move","reward":0,"time":7.216},{"nodeId":46,"eventType":"move","reward":0,"time":7.369},{"nodeId":46,"eventType":"collect","reward":0,"time":7.59},{"nodeId":47,"eventType":"move","reward":0,"time":7.786},{"nodeId":48,"eventType":"move","reward":0,"time":7.947},{"nodeId":49,"eventType":"move","reward":0,"time":8.101},{"nodeId":60,"eventType":"move","reward":0,"time":8.356},{"nodeId":60,"eventType":"finish","reward":0,"time":11.669}]}}