{"latency_ms":3,"trial_data":{"TrialEventData":[{"nodeId":71,"eventType":"move","reward":0,"time":1.049},{"nodeId":82,"eventType":"move","reward":0,"time":1.258},{"nodeId":93,"eventType":"move","reward":0,"time":1.447},{"nodeId":104,"eventType":"move","reward":0,"time":1.633},{"nodeId":105,"eventType":"move","reward":0,"time":1.875},{"nodeId":106,"eventType":"move","reward":0,"time":2.111},{"nodeId":106,"eventType":"collect","reward":0,"time":2.263},{"nodeId":105,"eventType":"move","reward":0,"time":2.489},{"nodeId":104,"eventType":"move","reward":0,"time":2.646},{"nodeId":103,"eventType":"move","reward":0,"time":2.775},{"nodeId":102,"eventType":"move","reward":0,"time":2.886},{"nodeId":101,"eventType":"move","reward":0,"time":3.014},{"nodeId":100,"eventType":"move","reward":0,"time":3.16},{"nodeId":100,"eventType":"collect","reward":0,"time":3.428},{"nodeId":89,"eventType":"move","reward":0,"time":3.712},{"nodeId":89,"eventType":"collect","reward":0,"time":3.845},{"nodeId":78,"eventType":"move","reward":0,"time":4.182},{"nodeId":79,"eventType":"move","reward":0,"time":4.431},{"nodeId":79,"eventType":"collect","reward":0,"time":4.714},{"nodeId":68,"eventType":"move","reward":0,"time":5.044},{"nodeId":67,"eventType":"move","reward":0,"time":5.278},{"nodeId":66,"eventType":"move","reward":0,"time":5.48},{"nodeId":66,"eventType":"collect","reward":0,"time":5.632},{"nodeId":67,"eventType":"move","reward":0,"time":5.943},{"nodeId":56,"eventType":"move","reward":0,"time":6.175},{"nodeId":45,"eventType":"move","reward":0,"time":6.361},{"nodeId":46,"eventType":"move","reward":0,"time":6.669},{"nodeId":46,"eventType":"collect","reward":0,"time":6.867},{"nodeId":35,"eventType":"move","reward":0,"time":7.409},{"nodeId":34,"eventType":"move","reward":0,"time":7.595},{"nodeId":34,"eventType":"collect","reward":0,"time":7.712},{"nodeId":23,"eventType":"move","reward":0,"time":8.063},{"nodeId":12,"eventType":"move","reward":0,"time":8.253},{"nodeId":11,"eventType":"move","reward":0,"time":8.613},{"nodeId":11,"eventType":"collect","reward":0,"time":8.765},{"nodeId":12,"eventType":"move","reward":0,"time":9.03},{"nodeId":13,"eventType":"move","reward":0,"time":9.249},{"nodeId":14,"eventType":"move","reward":0,"time":9.399},{"nodeId":15,"eventType":"move","reward":0,"time":9.544},{"nodeId":16,"eventType":"move","reward":0,"time":9.782},{"nodeId":17,"eventType":"move","reward":0,"time":9.902},{"nodeId":28,"eventType":"move","reward":0,"time":10.398},{"nodeId":39,"eventType":"move","reward":0,"time":11.016},{"nodeId":40,"eventType":"move","reward":0,"time":11.427},{"nodeId":29,"eventType":"move","reward":0,"time":11.863},{"nodeId":29,"eventType":"collect","reward":0,"time":12.147},{"nodeId":40,"eventType":"move","reward":0,"time":12.4},{"nodeId":51,"eventType":"move","reward":0,"time":12.548},{"nodeId":51,"eventType":"collect","reward":0,"time":12.716},{"nodeId":null,"eventType":"overfilled","reward":0,"time":12.73},{"nodeId":62,"eventType":"move","reward":0,"time":13.032},{"nodeId":73,"eventType":"move","reward":0,"time":13.202},{"nodeId":72,"eventType":"move","reward":0,"time":13.602},{"nodeId":71,"eventType":"move","reward":0,"time":13.767},{"nodeId":60,"eventType":"move","reward":0,"time":14.037}]}}