{"latency_ms":24,"trial_data":{"TrialEventData":[{"nodeId":71,"eventType":"move","reward":0,"time":1.61},{"nodeId":82,"eventType":"move","reward":0,"time":1.804},{"nodeId":93,"eventType":"move","reward":0,"time":1.988},{"nodeId":104,"eventType":"move","reward":0,"time":2.186},{"nodeId":103,"eventType":"move","reward":0,"time":2.391},{"nodeId":102,"eventType":"move","reward":0,"time":2.582},{"nodeId":102,"eventType":"collect","reward":0,"time":2.89},{"nodeId":113,"eventType":"move","reward":0,"time":3.072},{"nodeId":112,"eventType":"move","reward":0,"time":3.54},{"nodeId":112,"eventType":"collect","reward":0,"time":3.921},{"nodeId":101,"eventType":"move","reward":0,"time":4.116},{"nodeId":90,"eventType":"move","reward":0,"time":4.332},{"nodeId":79,"eventType":"move","reward":0,"time":4.476},{"nodeId":68,"eventType":"move","reward":0,"time":4.649},{"nodeId":57,"eventType":"move","reward":0,"time":4.818},{"nodeId":46,"eventType":"move","reward":0,"time":4.971},{"nodeId":35,"eventType":"move","reward":0,"time":5.372},{"nodeId":35,"eventType":"collect","reward":0,"time":5.649},{"nodeId":34,"eventType":"move","reward":0,"time":5.823},{"nodeId":34,"eventType":"collect","reward":0,"time":6.143},{"nodeId":45,"eventType":"move","reward":0,"time":6.349},{"nodeId":46,"eventType":"move","reward":0,"time":6.656},{"nodeId":47,"eventType":"move","reward":0,"time":6.875},{"nodeId":48,"eventType":"move","reward":0,"time":7.023},{"nodeId":59,"eventType":"move","reward":0,"time":7.244},{"nodeId":60,"eventType":"move","reward":0,"time":7.482},{"nodeId":60,"eventType":"finish","reward":0,"time":7.667}]}}